[
    {
        "name":"Abhiyuday Sharma",
        "id":"Aggressive,Polite",
        "image_url":"https://qph.cf2.quoracdn.net/main-qimg-6254dfe147d236e9168d01fc168d5b3e-lq",
        "rating":"7",
        "description":"sdhsfshhfvasfsh,jfzs,jvz,bjvzhjbdv,xjvbz,xvx,jvhvbdf.kejgsdbgs.kfdbg",
        "cast":"dangerous",
        "genere":["Romantic","comedy","funny"],
        "watch_url":"https://www.primevideo.com/detail/Mirzapur/0HV20AIVKWRM0Q9N6NCXO7DKD5"
    },
    {
        "name":"Abhiyuday Sharma",
        "id":"Aggressive,Polite",
        "image_url":"https://qph.cf2.quoracdn.net/main-qimg-6254dfe147d236e9168d01fc168d5b3e-lq",
        "rating":"7",
        "description":"sdhsfshhfvasfsh,jfzs,jvz,bjvzhjbdv,xjvbz,xvx,jvhvbdf.kejgsdbgs.kfdbg",
        "cast":"dangerous",
        "genere":["Romantic","comedy","funny"],
        "watch_url":"https://www.primevideo.com/detail/Mirzapur/0HV20AIVKWRM0Q9N6NCXO7DKD5"
    }
]